socksimap/__init__.py
socksimap-1.0.1.dist-info/LICENSE
socksimap-1.0.1.dist-info/METADATA
socksimap-1.0.1.dist-info/WHEEL
socksimap-1.0.1.dist-info/top_level.txt
socksimap-1.0.1.dist-info/RECORD
