Metadata-Version: 2.1
Name: socksimap
Version: 1.0.1
Summary: Connect to IMAP through Socks
Home-page: https://github.com/optinsoft/socksimap
Author: optinsoft
Author-email: optinsoft@gmail.com
Keywords: socks,imap
License-File: LICENSE
Requires-Dist: PySocks
